esi_utils_colors/__init__.py
esi_utils_colors/cpalette.py
esi_utils_colors-1.0.5.dist-info/licenses/LICENSE.md
esi_utils_colors-1.0.5.dist-info/METADATA
esi_utils_colors-1.0.5.dist-info/WHEEL
esi_utils_colors-1.0.5.dist-info/top_level.txt
esi_utils_colors-1.0.5.dist-info/RECORD
