Metadata-Version: 2.4
Name: esi-utils-colors
Version: 1.0.5
Summary: USGS Earthquake Impact Utilities for Colors
Author-email: Mike Hearne <mhearne@usgs.gov>
License: License
Keywords: losses,earthquake
Requires-Python: >=3.9
License-File: LICENSE.md
Requires-Dist: matplotlib>=3.1.0
Requires-Dist: numpy>=1.26
Requires-Dist: pandas>=1.0
Provides-Extra: dev
Requires-Dist: build>=0.9.0; extra == "dev"
Requires-Dist: black>=22.12.0; extra == "dev"
Requires-Dist: flake8>=6.0.0; extra == "dev"
Requires-Dist: ipython>=8.8.0; extra == "dev"
Requires-Dist: notebook>=6.5.2; extra == "dev"
Requires-Dist: twine>=4.0.2; extra == "dev"
Provides-Extra: test
Requires-Dist: pytest>=7.2.0; extra == "test"
Requires-Dist: pytest-cov>=4.0.0; extra == "test"
Requires-Dist: vcrpy>=4.2.0; extra == "test"
Provides-Extra: build
Requires-Dist: build; extra == "build"
Requires-Dist: twine; extra == "build"
Requires-Dist: check-wheel-contents; extra == "build"
Dynamic: license-file
